odoo/addons/hr_payroll_document/README.rst
odoo/addons/hr_payroll_document/__init__.py
odoo/addons/hr_payroll_document/__manifest__.py
odoo/addons/hr_payroll_document/data/email_payroll_employee.xml
odoo/addons/hr_payroll_document/i18n/ca_ES.po
odoo/addons/hr_payroll_document/i18n/es.po
odoo/addons/hr_payroll_document/i18n/hr_payroll_document.pot
odoo/addons/hr_payroll_document/i18n/it.po
odoo/addons/hr_payroll_document/models/__init__.py
odoo/addons/hr_payroll_document/models/hr_employee.py
odoo/addons/hr_payroll_document/models/ir_attachment.py
odoo/addons/hr_payroll_document/models/ir_attachment_payroll_custom.py
odoo/addons/hr_payroll_document/models/res_users.py
odoo/addons/hr_payroll_document/readme/CONTRIBUTORS.md
odoo/addons/hr_payroll_document/readme/DESCRIPTION.md
odoo/addons/hr_payroll_document/security/ir.model.access.csv
odoo/addons/hr_payroll_document/static/description/icon.png
odoo/addons/hr_payroll_document/static/description/index.html
odoo/addons/hr_payroll_document/tests/__init__.py
odoo/addons/hr_payroll_document/tests/test.docx
odoo/addons/hr_payroll_document/tests/test.pdf
odoo/addons/hr_payroll_document/tests/test_hr_payroll_document.py
odoo/addons/hr_payroll_document/views/hr_employee_views.xml
odoo/addons/hr_payroll_document/wizard/__init__.py
odoo/addons/hr_payroll_document/wizard/payroll_management_wizard.py
odoo/addons/hr_payroll_document/wizard/payroll_management_wizard.xml
odoo_addon_hr_payroll_document-17.0.1.1.1.dist-info/METADATA
odoo_addon_hr_payroll_document-17.0.1.1.1.dist-info/WHEEL
odoo_addon_hr_payroll_document-17.0.1.1.1.dist-info/top_level.txt
odoo_addon_hr_payroll_document-17.0.1.1.1.dist-info/RECORD
