Metadata-Version: 2.1
Name: odoo-addon-hr_payroll_document
Version: 17.0.1.1.1
Requires-Python: >=3.10
Requires-Dist: odoo>=17.0a,<17.1dev
Requires-Dist: pypdf
Summary: Manage payroll for each employee
Home-page: https://github.com/OCA/payroll
License: AGPL-3
Author: APSL, Odoo Community Association (OCA)
Author-email: support@odoo-community.org
Classifier: Programming Language :: Python
Classifier: Framework :: Odoo
Classifier: Framework :: Odoo :: 17.0
Classifier: License :: OSI Approved :: GNU Affero General Public License v3
